pyhobo/__init__.py
pyhobo/pyhobo.py
pyhobo-0.0.2.dist-info/LICENSE
pyhobo-0.0.2.dist-info/METADATA
pyhobo-0.0.2.dist-info/WHEEL
pyhobo-0.0.2.dist-info/top_level.txt
pyhobo-0.0.2.dist-info/RECORD
